zasca/__init__.py
zasca/main.py
zasca/scanner.py
zasca/utils.py
zasca/data/queries.yaml
zasca/maven_scanner/__init__.py
zasca/maven_scanner/maven_tree_generator.py
zasca/node_scanner/__init__.py
zasca/node_scanner/node_tree_generator.py
zasca/template/cyclonedx_template.json
zasca/template/report_template.html
zasca-2.1.0.dist-info/LICENSE
zasca-2.1.0.dist-info/METADATA
zasca-2.1.0.dist-info/WHEEL
zasca-2.1.0.dist-info/entry_points.txt
zasca-2.1.0.dist-info/top_level.txt
zasca-2.1.0.dist-info/RECORD
